chapicha/__init__.py
chapicha/cli.py
chapicha/extract.py
chapicha/transform.py
chapicha/ui/canvas.py
chapicha/util.py
chapicha-0.3.0.dist-info/entry_points.txt
chapicha-0.3.0.dist-info/LICENSE
chapicha-0.3.0.dist-info/WHEEL
chapicha-0.3.0.dist-info/METADATA
chapicha-0.3.0.dist-info/RECORD
